analytics/test/client.py
june/analytics/__init__.py
june/analytics/client.py
june/analytics/consumer.py
june/analytics/request.py
june/analytics/utils.py
june/analytics/version.py
june_analytics_python-2.3.0.dist-info/LICENSE
june_analytics_python-2.3.0.dist-info/METADATA
june_analytics_python-2.3.0.dist-info/WHEEL
june_analytics_python-2.3.0.dist-info/top_level.txt
june_analytics_python-2.3.0.dist-info/RECORD
